[
    {
      "id": 1,
      "zyczenia": "Świąteczny stół już ugina się od dobroci. Niech nigdy nie zabraknie jej w Twoim życiu. Żyj w zgodzie ze sobą, bądź zdrów. Nadchodzący rok niech będzie dla Ciebie niekończącym się pasmem sukcesów. Wspaniałych, rodzinnych Świąt Bożego Narodzenia",
      "autor": "Szymon"
    },
    {
      "id": 2,
      "zyczenia": "Szczęśliwego Nowego Roku!",
      "autor": "Jan Kowalski"
    },
    {
      "id": 3,
      "zyczenia": "Niech spełnią się wszystkie Twoje marzenia!",
      "autor": "Anna Nowak"
    }
  ]
  
